{"chunk_definitions":[{"row":24,"row_count":1,"visible":true,"expansion_state":0,"options":{"engine":"r","label":"setup","include":false},"document_id":"69103EE6","chunk_id":"csetup_chunk","chunk_label":"setup"},{"row":64,"row_count":1,"visible":true,"expansion_state":0,"options":{"engine":"r","label":"loading_movie_data"},"document_id":"69103EE6","chunk_id":"c8oish8jf80so","chunk_label":"loading_movie_data"},{"row":84,"row_count":1,"visible":true,"expansion_state":0,"options":{"engine":"r","label":"test_train_split"},"document_id":"69103EE6","chunk_id":"c741k96w2yzax","chunk_label":"test_train_split"},{"row":262,"row_count":1,"visible":true,"expansion_state":0,"options":{"engine":"r","label":"unnamed-chunk-14"},"document_id":"69103EE6","chunk_id":"cz0uh1dfywnrm","chunk_label":"unnamed-chunk-14"},{"row":287,"row_count":1,"visible":true,"expansion_state":0,"options":{"engine":"r","label":"unnamed-chunk-15"},"document_id":"69103EE6","chunk_id":"cl43c532tnlbg","chunk_label":"unnamed-chunk-15"},{"row":301,"row_count":1,"visible":true,"expansion_state":0,"options":{"engine":"r","label":"unnamed-chunk-16"},"document_id":"69103EE6","chunk_id":"cvhpad1cptzgw","chunk_label":"unnamed-chunk-16"},{"row":343,"row_count":1,"visible":true,"expansion_state":0,"options":{"engine":"r","label":"unnamed-chunk-17"},"document_id":"69103EE6","chunk_id":"ca9yibw5341ha","chunk_label":"unnamed-chunk-17"},{"row":360,"row_count":1,"visible":true,"expansion_state":0,"options":{"engine":"r","label":"unnamed-chunk-18"},"document_id":"69103EE6","chunk_id":"c6eyf6055m0fg","chunk_label":"unnamed-chunk-18"},{"row":373,"row_count":1,"visible":true,"expansion_state":0,"options":{"engine":"r","label":"unnamed-chunk-19"},"document_id":"69103EE6","chunk_id":"cnh6mha0y787q","chunk_label":"unnamed-chunk-19"},{"row":419,"row_count":1,"visible":true,"expansion_state":0,"options":{"engine":"r","label":"unnamed-chunk-21"},"document_id":"69103EE6","chunk_id":"cslo47y0vs4z5","chunk_label":"unnamed-chunk-20"},{"row":461,"row_count":1,"visible":true,"expansion_state":0,"options":{"engine":"r","label":"unnamed-chunk-22"},"document_id":"69103EE6","chunk_id":"ct7cajuxggqgz","chunk_label":"unnamed-chunk-21"},{"row":469,"row_count":1,"visible":true,"expansion_state":0,"options":{"engine":"r","label":"unnamed-chunk-23"},"document_id":"69103EE6","chunk_id":"cqf4u11yzj7dy","chunk_label":"unnamed-chunk-22"},{"row":492,"row_count":1,"visible":true,"expansion_state":0,"options":{"engine":"r","label":"unnamed-chunk-35"},"document_id":"69103EE6","chunk_id":"cl0eqeyx0u2x5","chunk_label":"unnamed-chunk-23"},{"row":517,"row_count":1,"visible":true,"expansion_state":0,"options":{"engine":"r","label":"unnamed-chunk-4"},"document_id":"69103EE6","chunk_id":"cbeceyrvrcyf1","chunk_label":"unnamed-chunk-25"},{"row":534,"row_count":1,"visible":true,"expansion_state":0,"options":{"engine":"r","label":"unnamed-chunk-5"},"document_id":"69103EE6","chunk_id":"cxg0zlksfzbik","chunk_label":"unnamed-chunk-26"}],"doc_write_time":1633858950}